os_vif/__init__.py
os_vif/exception.py
os_vif/i18n.py
os_vif/opts.py
os_vif/plugin.py
os_vif/utils.py
os_vif/version.py
os_vif/internal/__init__.py
os_vif/internal/ip/__init__.py
os_vif/internal/ip/api.py
os_vif/internal/ip/ip_command.py
os_vif/internal/ip/linux/__init__.py
os_vif/internal/ip/linux/impl_pyroute2.py
os_vif/objects/__init__.py
os_vif/objects/base.py
os_vif/objects/fields.py
os_vif/objects/fixed_ip.py
os_vif/objects/host_info.py
os_vif/objects/instance_info.py
os_vif/objects/network.py
os_vif/objects/route.py
os_vif/objects/subnet.py
os_vif/objects/vif.py
os_vif/tests/__init__.py
os_vif/tests/functional/__init__.py
os_vif/tests/functional/base.py
os_vif/tests/functional/privsep.py
os_vif/tests/functional/internal/__init__.py
os_vif/tests/functional/internal/command/__init__.py
os_vif/tests/functional/internal/command/ip/__init__.py
os_vif/tests/functional/internal/command/ip/test_impl_pyroute2.py
os_vif/tests/unit/__init__.py
os_vif/tests/unit/base.py
os_vif/tests/unit/test_base.py
os_vif/tests/unit/test_exception.py
os_vif/tests/unit/test_host_info.py
os_vif/tests/unit/test_objects.py
os_vif/tests/unit/test_os_vif.py
os_vif/tests/unit/test_vif.py
os_vif/tests/unit/internal/__init__.py
os_vif/tests/unit/internal/ip/__init__.py
os_vif/tests/unit/internal/ip/test_api.py
os_vif/tests/unit/internal/ip/linux/__init__.py
os_vif/tests/unit/internal/ip/linux/test_impl_pyroute2.py
vif_plug_linux_bridge/__init__.py
vif_plug_linux_bridge/constants.py
vif_plug_linux_bridge/iptables.py
vif_plug_linux_bridge/linux_bridge.py
vif_plug_linux_bridge/linux_net.py
vif_plug_linux_bridge/privsep.py
vif_plug_linux_bridge/tests/__init__.py
vif_plug_linux_bridge/tests/unit/__init__.py
vif_plug_linux_bridge/tests/unit/test_linux_net.py
vif_plug_linux_bridge/tests/unit/test_plugin.py
vif_plug_noop/__init__.py
vif_plug_noop/noop.py
vif_plug_noop/tests/__init__.py
vif_plug_noop/tests/unit/__init__.py
vif_plug_noop/tests/unit/test_plugin.py
vif_plug_ovs/__init__.py
os_vif-4.2.0.dist-info/AUTHORS
os_vif-4.2.0.dist-info/LICENSE
os_vif-4.2.0.dist-info/METADATA
os_vif-4.2.0.dist-info/WHEEL
os_vif-4.2.0.dist-info/entry_points.txt
os_vif-4.2.0.dist-info/pbr.json
os_vif-4.2.0.dist-info/top_level.txt
os_vif-4.2.0.dist-info/RECORD
